Workbook

Sheet Inputs
A1: Label | B1: Value
A2: Fleet Quantity | B2: 218
A3: IoT Logger Unit Cost | B3: 8755
A4: IoT Logger Margin | B4: 1.4
A5: Firmware/App Dev Cost | B5: 1070356.3
A6: SAP Integration Cost | B6: 593572.8
A7: Dev Margin | B7: 0.8
A8: Maintenance Cost | B8: 800000
A9: Maintenance Margin | B9: 1.1
A10: QR Device Unit Cost | B10: 26000
A11: QR Device Margin | B11: 0.6
A12: SaaS Platform (per unit/month) | B12: 550
A13: SaaS SMS (per unit/month) | B13: 150
... A34: Project Duration (years, for Grand Total) | B34: 1

Sheet IoT Logger Cost
A1: IoT Logger Cost
A2: Fleet Qty | B2: =Inputs!B2 -> 218
A3: Unit Cost | B3: =Inputs!B3 -> 8755
A4: Margin | B4: =Inputs!B4 -> 1.4
A5: Unit Price | B5: =B3*(1+B4) -> 21012
A6: Total Cost | B6: =B3*B2 -> 1908590
A7: Total Price | B7: =B5*B2 -> 4580616

Sheet Sensor Cost
A1: Sensor | B1: Qty | C1: Unit Cost | D1: Margin | E1: Unit Price | F1: Total Cost | G1: Total Price
A2: Fuel Sensor | B2: =Inputs!B26 -> 218 | C2: =Inputs!B16 -> 7350 | D2: =Inputs!B17 -> 1 | E2: =C2*(1+D2) -> 14700 | F2: =C2*B2 -> 1602300 | G2: =E2*B2 -> 3204600
A3: Temperature Sensor | B3: =Inputs!B27 -> 218 | C3: =Inputs!B18 -> 5050 | D3: =Inputs!B19 -> 0.65 | E3: =C3*(1+D3) -> 8332.5 | F3: =C3*B3 -> 1100900 | G3: =E3*B3 -> 1816485
A4: Pressure Sensor | B4: =Inputs!B28 -> 218 | C4: =Inputs!B20 -> 2850 | D4: =Inputs!B21 -> 0.7 | E4: =C4*(1+D4) -> 4845 | F4: =C4*B4 -> 621300 | G4: =E4*B4 -> 1056210
A5: Hydraulic Sensor | B5: =Inputs!B29 -> 218 | C5: =Inputs!B22 -> 5050 | D5: =Inputs!B23 -> 0.8 | E5: =C5*(1+D5) -> 9090 | F5: =C5*B5 -> 1100900 | G5: =E5*B5 -> 1981620
A6: TOTAL | F6: =SUM(F2:F5) -> 4425400 | G6: =SUM(G2:G5) -> 8058915

Sheet SaaS Cost
A1: SaaS Cost
A2: Platform (per unit/month) | B2: =Inputs!B12 -> 550
A3: SMS (per unit/month) | B3: =Inputs!B13 -> 150
A4: SIM (per unit/month) | B4: =Inputs!B14 -> 100
A5: Combined Unit Cost / Month | B5: =SUM(B2:B4) -> 800
A6: Margin | B6: =Inputs!B15 -> 0.7
A7: Unit Price / Month | B7: =B5*(1+B6) -> 1360
A8: Fleet Qty | B8: =Inputs!B2 -> 218
A9: Total Cost / Month | B9: =B5*B8 -> 174400
A10: Total Price / Month | B10: =B7*B8 -> 296480
A11: Months / Year | B11: =Inputs!B33 -> 12
A12: Annual Total Cost | B12: =B9*B11 -> 2092800
A13: Annual Total Price | B13: =B10*B11 -> 3557760

Sheet Dev & Maintenance
A1: Dev & Maintenance
A2: Firmware/App Dev Cost | B2: =Inputs!B5 -> 1070356.3
A3: SAP Integration Cost | B3: =Inputs!B6 -> 593572.8
A4: Dev Subtotal (Cost) | B4: =SUM(B2:B3) -> 1663929.1
A5: Dev Margin | B5: =Inputs!B7 -> 0.8
A6: Dev Total Price | B6: =B4*(1+B5) -> 2995072.4
A8: Maintenance Cost | B8: =Inputs!B8 -> 800000
A9: Maintenance Margin | B9: =Inputs!B9 -> 1.1
A10: Maintenance Price | B10: =B8*(1+B9) -> 1680000
A12: Combined Total Cost | B12: =B4+B8 -> 2463929.1
A13: Combined Total Price | B13: =B6+B10 -> 4675072.4

Sheet QR Device
A1: QR Device
A2: Unit Cost | B2: =Inputs!B10 -> 26000
A3: Margin | B3: =Inputs!B11 -> 0.6
A4: Qty | B4: =Inputs!B30 -> 1
A5: Unit Price | B5: =B2*(1+B3) -> 41600
A6: Total Cost | B6: =B2*B4 -> 26000
A7: Total Price | B7: =B5*B4 -> 41600

Sheet Installation
A1: Installation
A2: Rate / Day | B2: =Inputs!B24 -> 15000
A3: Install Days | B3: =Inputs!B31 -> 0
A4: Cost via Daily Rate | B4: =B2*B3 -> 0
A6: Rate / Month | B6: =Inputs!B25 -> 360000
A7: Install Months | B7: =Inputs!B32 -> 0
A8: Cost via Monthly Rate | B8: =B6*B7 -> 0
A10: Total Installation Cost | B10: =B4+B8 -> 0

Sheet Overall Summary
A1: Category | B1: Total Cost | C1: Total Price
A2: IoT Logger | B2: ='IoT Logger Cost'!B6 -> 1908590 | C2: ='IoT Logger Cost'!B7 -> 4580616
A3: Sensors | B3: ='Sensor Cost'!F6 -> 4425400 | C3: ='Sensor Cost'!G6 -> 8058915
A4: SaaS (Annual) | B4: ='SaaS Cost'!B12 -> 2092800 | C4: ='SaaS Cost'!B13 -> 3557760
A5: Dev & Maintenance | B5: ='Dev & Maintenance'!B12 -> 2463929.1 | C5: ='Dev & Maintenance'!B13 -> 4675072.4
A6: QR Device | B6: ='QR Device'!B6 -> 26000 | C6: ='QR Device'!B7 -> 41600
A7: Installation | B7: =Installation!B10 -> 0 | C7: =Installation!B10 -> 0
A8: TOTAL | B8: =SUM(B2:B7) -> 10916719 | C8: =SUM(C2:C7) -> 20913963

Sheet Proposal Cost Summary
A1: Proposal Cost Summary
A2: Total First-Year Cost | B2: ='Overall Summary'!C8 -> 20913963
A4: Project Duration (years) | B4: =Inputs!B34 -> 1
A5: Recurring Categories, Annual (SaaS + Maintenance, at Price) | B5: ='SaaS Cost'!B13+'Dev & Maintenance'!B10 -> 5237760
A6: Additional Years Beyond Year 1 | B6: =MAX(B4-1,0)*B5 -> 0
A8: Grand Total | B8: =B2+B6 -> 20913963

Sheet ROI Inputs
A1: Benefit Line | B1: Value (₹/year) | C1: Driven By
A2: Fuel Savings (₹/year) | B2: 0 | C2: Fuel Sensor
A3: Downtime Cost Avoided (₹/year) | B3: 0 | C3: Temperature / Pressure / Hydraulic Sensor + IoT Logger Alerts
A4: Manpower Cost Saved (₹/year) | B4: 0 | C4: QR Scanner + SaaS Platform (dispatch accuracy)
A5: (Additional Benefit Category — NEEDS INPUT FROM SATHISHKUMAR) | B5: 0 | C5: (NEEDS INPUT — which device/sensor drives this)
A6: Total Annual Savings | B6: =SUM(B2:B5) -> 0

Sheet Current vs New
A1: Line | B1: Current State (without IoT) | C1: Savings / Benefit | D1: New State (with IoT)
A2: Fuel Savings (₹/year) | B2: 0 | C2: =B2 -> 0 | D2: =B2-C2 -> 0
A3: Downtime Cost Avoided (₹/year) | B3: 0 | C3: =B3 -> 0 | D3: =B3-C3 -> 0
A4: Manpower Cost Saved (₹/year) | B4: 0 | C4: =B4 -> 0 | D4: =B4-C4 -> 0
A5: (Additional Benefit Category — NEEDS INPUT FROM SATHISHKUMAR) | B5: 0 | C5: =B5 -> 0 | D5: =B5-C5 -> 0

Sheet Site-by-Site ROI
A1: Site | B1: Fleet Count | C1: Allocated Cost | D1: Allocated Savings | E1: Payback (months)
A2: (Site 1 — NEEDS INPUT FROM SATHISHKUMAR: real site name) | B2: 0 | C2: =IFERROR(B2/Inputs!B2*'Proposal Cost Summary'!B8,0) -> 0 | D2: =IFERROR(B2/Inputs!B2*'ROI Inputs'!B6,0) -> 0 | E2: =IFERROR(C2/(D2/12),"N/A") -> N/A
A3: (Site 2 — NEEDS INPUT FROM SATHISHKUMAR: real site name) | B3: 0 | C3: =IFERROR(B3/Inputs!B2*'Proposal Cost Summary'!B8,0) -> 0 | D3: =IFERROR(B3/Inputs!B2*'ROI Inputs'!B6,0) -> 0 | E3: =IFERROR(C3/(D3/12),"N/A") -> N/A
A4: (Site 3 — NEEDS INPUT FROM SATHISHKUMAR: real site name) | B4: 0 | C4: =IFERROR(B4/Inputs!B2*'Proposal Cost Summary'!B8,0) -> 0 | D4: =IFERROR(B4/Inputs!B2*'ROI Inputs'!B6,0) -> 0 | E4: =IFERROR(C4/(D4/12),"N/A") -> N/A
A5: TOTAL (placeholder sites) | B5: =SUM(B2:B4) -> 0 | C5: =SUM(C2:C4) -> 0 | D5: =SUM(D2:D4) -> 0

Sheet ROI Summary
A1: ROI Summary
A2: Total Investment | B2: ='Proposal Cost Summary'!B8 -> 20913963
A3: Total Annual Savings | B3: ='ROI Inputs'!B6 -> 0
A4: Recurring Annual Cost (SaaS + Maintenance, at Price) | B4: ='Proposal Cost Summary'!B5 -> 5237760
A5: Net Annual Benefit | B5: =B3-B4 -> -5237760
A6: Payback Period (months) | B6: =IFERROR(B2/(B5/12),"N/A — no positive net benefit yet") -> -47.915055
A7: 3-Year Cumulative ROI % | B7: =IFERROR((B5*3-B2)/B2,"N/A") -> -1.7513296
